carasdk/__init__.py
carasdk/agent_framework.py
carasdk/global_sdk.py
carasdk/ipc_pb2.py
carasdk/ipc_pb2.pyi
carasdk/ipc_sdk.py
carasdk/log_config.py
carasdk/memory.py
carasdk/prompt.py
carasdk/prompt_v1.py
carasdk/stream_utils.py
carasdk/utils.py
carasdk-0.12.dist-info/METADATA
carasdk-0.12.dist-info/WHEEL
carasdk-0.12.dist-info/top_level.txt
carasdk-0.12.dist-info/RECORD
