Metadata-Version: 2.1
Name: carasdk
Version: 0.12
Summary: Cara Application Framework
Author-email: Humanify Organization <public@humanify.org>
Requires-Dist: protobuf>=5.27.3
Requires-Dist: colorlog>=6.8.2
Requires-Dist: uuid>=1.3.0
Requires-Dist: pyzmq>=26.1.1
Requires-Dist: pyyaml>=6.0.2
